horillactl/__init__.py
horillactl/ctl.py
horillactl-1.0.0.dist-info/METADATA
horillactl-1.0.0.dist-info/WHEEL
horillactl-1.0.0.dist-info/entry_points.txt
horillactl-1.0.0.dist-info/top_level.txt
horillactl-1.0.0.dist-info/RECORD
