Metadata-Version: 2.4
Name: horillactl
Version: 1.0.0
Summary: CLI tool to build and manage Horilla projects
Author: Horilla Team
Author-email: support@horilla.com
Classifier: Programming Language :: Python :: 3
Classifier: Operating System :: OS Independent
Classifier: Topic :: Software Development :: Build Tools
Requires-Python: >=3.10
Dynamic: author
Dynamic: author-email
Dynamic: classifier
Dynamic: requires-python
Dynamic: summary
